maleo/logging/__init__.py
maleo/logging/config.py
maleo/logging/enums.py
maleo/logging/logger.py
maleo_logging-0.0.46.dist-info/licenses/LICENSE
maleo_logging-0.0.46.dist-info/METADATA
maleo_logging-0.0.46.dist-info/WHEEL
maleo_logging-0.0.46.dist-info/top_level.txt
maleo_logging-0.0.46.dist-info/RECORD
